Tichonet_DL5/DL4.py
Tichonet_DL5/__init__.py
tichonet_dl5-0.0.2.dist-info/METADATA
tichonet_dl5-0.0.2.dist-info/WHEEL
tichonet_dl5-0.0.2.dist-info/licenses/LICENSE
tichonet_dl5-0.0.2.dist-info/RECORD
