Metadata-Version: 2.1
Name: Tichonet_DL5
Version: 0.0.2
Summary: Deep Learning functions, classes and requirements package. The complete set!
Project-URL: Homepage, https://github.com/SkipperCMD/Tichonet-DL5
Project-URL: Bug Tracker, https://github.com/SkipperCMD/Tichonet-DL5-Bug-Tracker
Author-email: TichonetDataScience - Yannay Rosenblatt <skipper.cmd@gmail.com>
License: MIT License
License-File: LICENSE
Classifier: License :: OSI Approved :: MIT License
Classifier: Operating System :: OS Independent
Classifier: Programming Language :: Python
Requires-Python: >=3.8
